gintel/__init__.py
gintel/cli.py
gintel/core.py
gintel/env.py
gintel/obj.py
gintel/utils.py
gintel/web.py
gintel-0.0.1.dist-info/LICENSE
gintel-0.0.1.dist-info/METADATA
gintel-0.0.1.dist-info/WHEEL
gintel-0.0.1.dist-info/entry_points.txt
gintel-0.0.1.dist-info/top_level.txt
gintel-0.0.1.dist-info/RECORD
