Metadata-Version: 2.1
Name: gintel
Version: 0.0.1
Home-page: https://github.com/harttraveller/gintel
Author: Hart Traveller
License: MIT
License-File: LICENSE
Requires-Dist: click
Requires-Dist: requests
Requires-Dist: pyeio
Requires-Dist: pillow
Requires-Dist: rich
